honeybee_grasshopper_energy/__init__.py
honeybee_grasshopper_energy/src/HB Adaptive Comfort Map.py
honeybee_grasshopper_energy/src/HB Adiabatic by Type.py
honeybee_grasshopper_energy/src/HB Airflow Newtwork.py
honeybee_grasshopper_energy/src/HB All-Air HVAC.py
honeybee_grasshopper_energy/src/HB Annual Loads.py
honeybee_grasshopper_energy/src/HB Apply Absolute Load Values.py
honeybee_grasshopper_energy/src/HB Apply ConstructionSet.py
honeybee_grasshopper_energy/src/HB Apply Daylight Control.py
honeybee_grasshopper_energy/src/HB Apply Load Values.py
honeybee_grasshopper_energy/src/HB Apply Opaque Construction.py
honeybee_grasshopper_energy/src/HB Apply ProgramType.py
honeybee_grasshopper_energy/src/HB Apply Room Schedules.py
honeybee_grasshopper_energy/src/HB Apply Setpoint Values.py
honeybee_grasshopper_energy/src/HB Apply Shade Construction.py
honeybee_grasshopper_energy/src/HB Apply Shade Schedule.py
honeybee_grasshopper_energy/src/HB Apply Window Construction.py
honeybee_grasshopper_energy/src/HB Balance Temperature.py
honeybee_grasshopper_energy/src/HB Blend ProgramTypes.py
honeybee_grasshopper_energy/src/HB Blind Material.py
honeybee_grasshopper_energy/src/HB Blower Pressure Converter.py
honeybee_grasshopper_energy/src/HB Carbon Emission Intensity.py
honeybee_grasshopper_energy/src/HB Color Faces.py
honeybee_grasshopper_energy/src/HB Color Rooms.py
honeybee_grasshopper_energy/src/HB Constant Schedule.py
honeybee_grasshopper_energy/src/HB Construction Set by Climate.py
honeybee_grasshopper_energy/src/HB ConstructionSet.py
honeybee_grasshopper_energy/src/HB Create OSM Measure.py
honeybee_grasshopper_energy/src/HB Custom Simulation Output.py
honeybee_grasshopper_energy/src/HB Custom Window Gap Material.py
honeybee_grasshopper_energy/src/HB DOAS HVAC.py
honeybee_grasshopper_energy/src/HB Deconstruct Construction.py
honeybee_grasshopper_energy/src/HB Deconstruct ConstructionSet Interior.py
honeybee_grasshopper_energy/src/HB Deconstruct ConstructionSet.py
honeybee_grasshopper_energy-1.59.5.dist-info/LICENSE
honeybee_grasshopper_energy-1.59.5.dist-info/METADATA
honeybee_grasshopper_energy-1.59.5.dist-info/WHEEL
honeybee_grasshopper_energy-1.59.5.dist-info/top_level.txt
honeybee_grasshopper_energy-1.59.5.dist-info/RECORD
