Metadata-Version: 2.1
Name: honeybee-grasshopper-energy
Version: 1.59.5
Summary: Honeybee Energy plugin for Grasshopper.
Home-page: https://github.com/ladybug-tools/honeybee-grasshopper-energy
Author: Ladybug Tools
Author-email: info@ladybug.tools
License: AGPL-3.0
Classifier: Programming Language :: Python :: 3.7
Classifier: Programming Language :: Python :: Implementation :: IronPython
Classifier: License :: OSI Approved :: GNU Affero General Public License v3
Classifier: Operating System :: OS Independent
License-File: LICENSE
